Metadata-Version: 1.1
Name: powder
Version: 0.9.1
Summary: A python package to simulate powder diffraction using CCP4 and xprepx.
Home-page: https://pypi.python.org/pypi/powder/
Author: James C. Stroud
Author-email: xtald00d@gmail.com
License: BSD
Platform: UNKNOWN
Classifier: Programming Language :: Python :: 2.6
Classifier: Programming Language :: Python :: 2.7
